brogcursor-0.1.2.dist-info/licenses/LICENSE
brogscursor/__init__.py
brogscursor/cli.py
brogscursor/recorder.py
brogscursor/utils.py
brogcursor-0.1.2.dist-info/METADATA
brogcursor-0.1.2.dist-info/WHEEL
brogcursor-0.1.2.dist-info/entry_points.txt
brogcursor-0.1.2.dist-info/top_level.txt
brogcursor-0.1.2.dist-info/RECORD
