Metadata-Version: 2.4
Name: brogcursor
Version: 0.1.2
Summary: Precise mouse and keyboard action recorder and replayer
Home-page: https://github.com/gnanesh-16/brogcursor
Author: Gnanesh
Author-email: Gnanesh <gnaneshbalusa016g@gmail.com>
Maintainer-email: Gnanesh <gnaneshbalusa016g@gmail.com>
License: MIT
Project-URL: Homepage, https://github.com/gnanesh-16/brogcursor
Project-URL: Issues, https://github.com/gnanesh-16/brogcursor/issues
Project-URL: Documentation, https://github.com/gnanesh-16/brogcursor#readme
Keywords: mouse,keyboard,record,replay,automation
Classifier: Programming Language :: Python :: 3
Classifier: License :: OSI Approved :: MIT License
Classifier: Operating System :: OS Independent
Classifier: Topic :: Utilities
Requires-Python: >=3.6
License-File: LICENSE
Requires-Dist: pyautogui>=0.9.53
Requires-Dist: pynput>=1.7.6
Requires-Dist: rich>=12.5.0
Dynamic: author
Dynamic: home-page
Dynamic: license-file
Dynamic: requires-python
